py_database/__init__.py
py_database/server.py
py_database_gilaxy04-0.0.1.dist-info/LICENSE
py_database_gilaxy04-0.0.1.dist-info/METADATA
py_database_gilaxy04-0.0.1.dist-info/WHEEL
py_database_gilaxy04-0.0.1.dist-info/top_level.txt
py_database_gilaxy04-0.0.1.dist-info/RECORD
