Metadata-Version: 2.1
Name: py_database_gilaxy04
Version: 0.0.1
Summary: database in python made simple
Author: Geoloup Team
Author-email: geoloupo team <franckiebbb@gmail.com>
Project-URL: Homepage, https://github.com/franck403/py_database
Project-URL: Bug Tracker, https://github.com/franck403/py_database/issues
Classifier: Programming Language :: Python :: 3
Classifier: License :: OSI Approved :: MIT License
Classifier: Operating System :: OS Independent
Requires-Python: >=3.7
License-File: LICENSE
